telebaka_anonymous_chat/__init__.py
telebaka_anonymous_chat/admin.py
telebaka_anonymous_chat/bot.py
telebaka_anonymous_chat/models.py
telebaka_anonymous_chat/tasks.py
telebaka_anonymous_chat/migrations/0001_initial.py
telebaka_anonymous_chat/migrations/0002_user_media_sent.py
telebaka_anonymous_chat/migrations/__init__.py
telebaka_anonymous_chat-0.1.23.dist-info/METADATA
telebaka_anonymous_chat-0.1.23.dist-info/RECORD
telebaka_anonymous_chat-0.1.23.dist-info/WHEEL
telebaka_anonymous_chat-0.1.23.dist-info/top_level.txt
